{
  "type" : "FeatureCollection",
  "features" : [{"type":"Feature","id":1,"geometry":{"type":"Point","coordinates":[-122.48391409389988,45.554438060895208]},"properties":{"OBJECTID":1,"title_en":"Wildlife Pond and Mitigation Wetlands","directions_en":"N side of NE Airport Way","content_en":"There is a walk-in access on the north side of the road. No parking.","title_es":null,"directions_es":null,"content_es":null,"title_ru":null,"directions_ru":null,"content_ru":null,"title_uk":null,"directions_uk":null,"content_uk":null}},{"type":"Feature","id":2,"geometry":{"type":"Point","coordinates":[-122.48727033814193,45.552333819419687]},"properties":{"OBJECTID":2,"title_en":"Mason Flats Wetland","directions_en":"S side of NE Airport Way","content_en":"This restored wetland provides excellent habitat for wildlife and many bird species. The NE Airport Way sidewalk provides excellent views, and this area can also be accessed by paddling from the Portland Water Bureau launch.","title_es":null,"directions_es":null,"content_es":null,"title_ru":null,"directions_ru":null,"content_ru":null,"title_uk":null,"directions_uk":null,"content_uk":null}},{"type":"Feature","id":3,"geometry":{"type":"Point","coordinates":[-122.48461656297734,45.552862164636331]},"properties":{"OBJECTID":3,"title_en":"Slough Trail","directions_en":"Access to the trail is from the south side of NE Airport Way.","content_en":"A trail extends to the NE 185th Ave city boundary, passing\r\nwetlands and a stormwater treatment pond\r\nalong the way. The area is planted with\r\nnative vegetation.","title_es":null,"directions_es":null,"content_es":null,"title_ru":null,"directions_ru":null,"content_ru":null,"title_uk":null,"directions_uk":null,"content_uk":null}}]
}